README.md
setup.cfg
setup.py
hospital_logfile_analyzer/__init__.py
hospital_logfile_analyzer/__main__.py
hospital_logfile_analyzer.egg-info/PKG-INFO
hospital_logfile_analyzer.egg-info/SOURCES.txt
hospital_logfile_analyzer.egg-info/dependency_links.txt
hospital_logfile_analyzer.egg-info/top_level.txt
hospital_logfile_analyzer/parsers/__init__.py
hospital_logfile_analyzer/parsers/cloverleaf_parser.py
hospital_logfile_analyzer/parsers/logfile_parser.py
hospital_logfile_analyzer/test/__init__.py
hospital_logfile_analyzer/test/test_cloverleaf_parser.py