Metadata-Version: 2.1
Name: hospital-logfile-analyzer
Version: 0.1.4
Summary: Tool to convert plain-text hospital integration engines' log files to structured data
Home-page: https://github.com/doctolib/hospital_logfile_analyzer
Author: Pavlo Dyban (Doctolib GmbH)
Author-email: pavlo.dyban@doctolib.com
License: MIT
Download-URL: https://github.com/doctolib/hospital_logfile_analyzer/archive/v.0.1.4.tar.gz
Keywords: logfile,parser,integration engine,communication server,HIS,hospital,information system,communication,TCP/IP,structured data
Platform: UNKNOWN
Classifier: Development Status :: 5 - Production/Stable
Classifier: Intended Audience :: System Administrators
Classifier: Intended Audience :: Developers
Classifier: Topic :: Internet :: Log Analysis
Classifier: License :: OSI Approved :: MIT License
Classifier: Programming Language :: Python :: 3
Classifier: Programming Language :: Python :: 3.4
Classifier: Programming Language :: Python :: 3.5
Classifier: Programming Language :: Python :: 3.6
Classifier: Programming Language :: Python :: 3.7
Classifier: Programming Language :: Python :: 3.8
